scalebaron/__init__.py
scalebaron/download.py
scalebaron/muaddata.py
scalebaron/scalebaron.py
scalebaron-1.0.0.dist-info/licenses/LICENSE
scalebaron-1.0.0.dist-info/METADATA
scalebaron-1.0.0.dist-info/WHEEL
scalebaron-1.0.0.dist-info/entry_points.txt
scalebaron-1.0.0.dist-info/top_level.txt
scalebaron-1.0.0.dist-info/RECORD
